sphinx_sitemap/__init__.py
sphinx_sitemap-2.8.0.dist-info/licenses/LICENSE
sphinx_sitemap-2.8.0.dist-info/METADATA
sphinx_sitemap-2.8.0.dist-info/WHEEL
sphinx_sitemap-2.8.0.dist-info/top_level.txt
sphinx_sitemap-2.8.0.dist-info/RECORD
